{"rigidBodies":[{"name":"huge-curve","imagePath":"../obstacles2_output/huge-curve.png","origin":{"x":500,"y":68.5},"polygons":[[{"x":987,"y":123},{"x":987,"y":131},{"x":968,"y":128},{"x":899,"y":101}],[{"x":156,"y":83},{"x":80,"y":108},{"x":38,"y":94},{"x":68,"y":79},{"x":124,"y":60}],[{"x":124,"y":60},{"x":212,"y":36},{"x":225,"y":65},{"x":156,"y":83}],[{"x":212,"y":36},{"x":280,"y":22},{"x":312,"y":48},{"x":225,"y":65}],[{"x":280,"y":22},{"x":365,"y":10},{"x":450,"y":4},{"x":448,"y":34},{"x":312,"y":48}],[{"x":450,"y":4},{"x":525,"y":3},{"x":553,"y":35},{"x":448,"y":34}],[{"x":525,"y":3},{"x":615,"y":8},{"x":707,"y":20},{"x":671,"y":45},{"x":553,"y":35}],[{"x":707,"y":20},{"x":787,"y":36},{"x":747,"y":59},{"x":671,"y":45}],[{"x":787,"y":36},{"x":858,"y":55},{"x":821,"y":77},{"x":747,"y":59}],[{"x":858,"y":55},{"x":931,"y":79},{"x":994,"y":104},{"x":994,"y":114},{"x":987,"y":123},{"x":899,"y":101},{"x":821,"y":77}],[{"x":80,"y":108},{"x":14,"y":134},{"x":9,"y":124},{"x":3,"y":107},{"x":24,"y":96},{"x":38,"y":94}]],"circles":[],"shapes":[{"type":"POLYGON","vertices":[{"x":14,"y":134},{"x":80,"y":108},{"x":156,"y":83},{"x":225,"y":65},{"x":312,"y":48},{"x":448,"y":34},{"x":553,"y":35},{"x":671,"y":45},{"x":747,"y":59},{"x":821,"y":77},{"x":899,"y":101},{"x":968,"y":128},{"x":987,"y":131},{"x":987,"y":123},{"x":994,"y":114},{"x":994,"y":104},{"x":931,"y":79},{"x":858,"y":55},{"x":787,"y":36},{"x":707,"y":20},{"x":615,"y":8},{"x":525,"y":3},{"x":450,"y":4},{"x":365,"y":10},{"x":280,"y":22},{"x":212,"y":36},{"x":124,"y":60},{"x":68,"y":79},{"x":38,"y":94},{"x":24,"y":96},{"x":3,"y":107},{"x":9,"y":124}]}]}],"dynamicObjects":[]}