{"rigidBodies":[{"name":"Root7","imagePath":"../root/Root7.png","origin":{"x":74.5,"y":192.5},"polygons":[[{"x":21,"y":362},{"x":16,"y":372},{"x":12,"y":371},{"x":4,"y":348},{"x":6,"y":338}],[{"x":6,"y":338},{"x":3,"y":339},{"x":9,"y":307},{"x":15,"y":294}],[{"x":8,"y":276},{"x":4,"y":274},{"x":13,"y":252},{"x":25,"y":237}],[{"x":20,"y":178},{"x":21,"y":155},{"x":23,"y":158},{"x":24,"y":191}],[{"x":24,"y":191},{"x":17,"y":182},{"x":20,"y":178}],[{"x":23,"y":158},{"x":29,"y":151},{"x":34,"y":154},{"x":27,"y":212},{"x":24,"y":191}],[{"x":44,"y":131},{"x":46,"y":106},{"x":50,"y":99},{"x":51,"y":109}],[{"x":65,"y":69},{"x":54,"y":64},{"x":48,"y":49},{"x":49,"y":39},{"x":53,"y":36}],[{"x":53,"y":19},{"x":46,"y":13},{"x":48,"y":8},{"x":62,"y":10},{"x":71,"y":20}],[{"x":71,"y":20},{"x":75,"y":13},{"x":73,"y":25}],[{"x":76,"y":28},{"x":84,"y":23},{"x":92,"y":36},{"x":96,"y":56}],[{"x":96,"y":56},{"x":89,"y":71},{"x":69,"y":78},{"x":65,"y":69},{"x":53,"y":36},{"x":53,"y":19},{"x":73,"y":25},{"x":76,"y":28}],[{"x":53,"y":19},{"x":71,"y":20},{"x":73,"y":25}],[{"x":89,"y":71},{"x":89,"y":82},{"x":62,"y":96},{"x":69,"y":78}],[{"x":96,"y":94},{"x":108,"y":103},{"x":40,"y":149},{"x":44,"y":131},{"x":51,"y":109},{"x":62,"y":96}],[{"x":62,"y":96},{"x":89,"y":82},{"x":96,"y":94}],[{"x":126,"y":103},{"x":126,"y":96},{"x":130,"y":113}],[{"x":130,"y":113},{"x":121,"y":107},{"x":126,"y":103}],[{"x":114,"y":215},{"x":113,"y":235},{"x":106,"y":251},{"x":97,"y":259},{"x":25,"y":237},{"x":27,"y":212}],[{"x":27,"y":212},{"x":34,"y":154},{"x":40,"y":149},{"x":108,"y":103},{"x":121,"y":107},{"x":130,"y":113}],[{"x":130,"y":113},{"x":137,"y":120},{"x":143,"y":140},{"x":142,"y":157},{"x":133,"y":182},{"x":114,"y":215},{"x":27,"y":212}],[{"x":88,"y":295},{"x":90,"y":306},{"x":81,"y":311},{"x":84.98489379882812,"y":298.32080078125}],[{"x":92,"y":276},{"x":94,"y":283},{"x":88,"y":295},{"x":84.98489379882812,"y":298.32080078125}],[{"x":81,"y":311},{"x":15,"y":294},{"x":8,"y":276},{"x":25,"y":237},{"x":97,"y":259},{"x":92,"y":276}],[{"x":81,"y":311},{"x":69,"y":344},{"x":53,"y":356},{"x":26,"y":363},{"x":21,"y":362},{"x":6,"y":338},{"x":15,"y":294}],[{"x":53,"y":356},{"x":47,"y":367},{"x":34,"y":375},{"x":21,"y":377},{"x":21,"y":373},{"x":26,"y":363}]],"circles":[],"shapes":[{"type":"POLYGON","vertices":[{"x":21,"y":377},{"x":34,"y":375},{"x":47,"y":367},{"x":53,"y":356},{"x":69,"y":344},{"x":81,"y":311},{"x":90,"y":306},{"x":88,"y":295},{"x":94,"y":283},{"x":92,"y":276},{"x":97,"y":259},{"x":106,"y":251},{"x":113,"y":235},{"x":114,"y":215},{"x":133,"y":182},{"x":142,"y":157},{"x":143,"y":140},{"x":137,"y":120},{"x":130,"y":113},{"x":126,"y":96},{"x":126,"y":103},{"x":121,"y":107},{"x":108,"y":103},{"x":96,"y":94},{"x":89,"y":82},{"x":89,"y":71},{"x":96,"y":56},{"x":92,"y":36},{"x":84,"y":23},{"x":76,"y":28},{"x":73,"y":25},{"x":75,"y":13},{"x":71,"y":20},{"x":62,"y":10},{"x":48,"y":8},{"x":46,"y":13},{"x":53,"y":19},{"x":53,"y":36},{"x":49,"y":39},{"x":48,"y":49},{"x":54,"y":64},{"x":65,"y":69},{"x":69,"y":78},{"x":62,"y":96},{"x":51,"y":109},{"x":50,"y":99},{"x":46,"y":106},{"x":44,"y":131},{"x":40,"y":149},{"x":34,"y":154},{"x":29,"y":151},{"x":23,"y":158},{"x":21,"y":155},{"x":20,"y":178},{"x":17,"y":182},{"x":24,"y":191},{"x":27,"y":212},{"x":25,"y":237},{"x":13,"y":252},{"x":4,"y":274},{"x":8,"y":276},{"x":15,"y":294},{"x":9,"y":307},{"x":3,"y":339},{"x":6,"y":338},{"x":4,"y":348},{"x":12,"y":371},{"x":16,"y":372},{"x":21,"y":362},{"x":26,"y":363},{"x":21,"y":373}]}]}],"dynamicObjects":[]}